{
  "name": "glycine",
  "carboxyl_pka": 2.34,
  "amino_pka": 9.6,
  "pi": 5.97,
  "states": ['../assets/images/glycine1.png',
             '../assets/images/glycine2.png',
             '../assets/images/glycine3.png']
},
{
  "name": "alanine",
  "carboxyl_pka": 2.34,
  "amino_pka": 9.69,
  "pi": 6.00,
  "states": ['../assets/images/alanine1.png',
             '../assets/images/alanine2.png',
             '../assets/images/alanine3.png']
},
{
  "name": "valine",
  "carboxyl_pka": 2.32,
  "amino_pka": 9.62,
  "pi": 5.96,
  "states": ['../assets/images/valine1.png',
             '../assets/images/valine2.png',
             '../assets/images/valine3.png']
},
{
  "name": "leucine",
  "carboxyl_pka": 2.36,
  "amino_pka": 9.60,
  "pi": 5.98,
  "states": ['../assets/images/leucine1.png',
             '../assets/images/leucine2.png',
             '../assets/images/leucine3.png']
},
{
  "name": "isoleucine",
  "carboxyl_pka": 2.36,
  "amino_pka": 9.6,
  "pi": 6.02,
  "states": ['../assets/images/isoleucine1.png',
             '../assets/images/isoleucine2.png',
             '../assets/images/isoleucine3.png']
},
{
  "name": "methionine",
  "carboxyl_pka": 2.28,
  "amino_pka": 9.21,
  "pi": 5.74,
  "states": ['../assets/images/methionine1.png',
             '../assets/images/methionine2.png',
             '../assets/images/methionine3.png']
},
{
  "name": "proline",
  "carboxyl_pka": 1.99,
  "amino_pka": 10.60,
  "pi": 6.30,
  "states": ['../assets/images/proline1.png',
             '../assets/images/proline2.png',
             '../assets/images/proline3.png']
},
{
  "name": "phenylalanine",
  "carboxyl_pka": 1.83,
  "amino_pka": 9.13,
  "pi": 5.48,
  "states": ['../assets/images/phenylalanine1.png',
             '../assets/images/phenylalanine2.png',
             '../assets/images/phenylalanine3.png']
},
{
  "name": "tryptophan",
  "carboxyl_pka": 2.83,
  "amino_pka": 9.39,
  "pi": 5.89,
  "states": ['../assets/images/tryptophan1.png',
             '../assets/images/tryptophan2.png',
             '../assets/images/tryptophan3.png']
},
{
  "name": "asparagine",
  "carboxyl_pka": 2.02,
  "amino_pka": 8.80,
  "pi": 5.41,
  "states": ['../assets/images/asparagine.png',
             '../assets/images/asparagine.png',
             '../assets/images/asparagine.png']
},
{
  "name": "glutamine",
  "carboxyl_pka": 2.17,
  "amino_pka": 9.13,
  "pi": 5.65,
  "states": ['../assets/images/glutamine1.png',
             '../assets/images/glutamine2.png',
             '../assets/images/glutamine3.png']
},
{
  "name": "serine",
  "carboxyl_pka": 2.21,
  "amino_pka": 9.15,
  "pi": 5.68,
  "states": ['../assets/images/serine1.png',
             '../assets/images/serine2.png',
             '../assets/images/serine3.png']
},
{
  "name": "threonine",
  "carboxyl_pka": 2.09,
  "amino_pka": 9.10,
  "pi": 5.60,
  "states": ['../assets/images/threonine1.png',
             '../assets/images/threonine2.png',
             '../assets/images/threonine3.png']
},
{
  "name": "tyrosine",
  "carboxyl_pka": 2.20,
  "amino_pka": 9.11,
  "pi": 5.66,
  "states": ['../assets/images/tyrosine1.png',
             '../assets/images/tyrosine2.png',
             '../assets/images/tyrosine3.png']
},
{
  "name": "cysteine",
  "carboxyl_pka": 1.96,
  "amino_pka": 8.18,
  "pi": 5.07,
  "states": ['../assets/images/cysteine1.png',
             '../assets/images/cysteine2.png',
             '../assets/images/cysteine3.png']
},
{
  "name": "aspartate",
  "carboxyl_pka": 1.88,
  "amino_pka": 9.60,
  "side_pka": 3.65,
  "pi": 2.77,
  "states": ['../assets/images/aspartate1.png',
             '../assets/images/aspartate2.png',
             '../assets/images/aspartate3.png',
             '../assets/images/aspartate.png']
},
{
  "name": "glutamate",
  "carboxyl_pka": 2.19,
  "amino_pka": 9.67,
  "side_pka": 4.25,
  "pi": 3.22,
  "states": ['../assets/images/glutamate1.png',
             '../assets/images/glutamate2.png',
             '../assets/images/glutamate3.png',
             '../assets/images/glutamate4.png']
},
{
  "name": "lysine",
  "carboxyl_pka": 2.18,
  "amino_pka": 8.95,
  "side_pka": 10.53,
  "pi": 9.74,
  "states": ['../assets/images/lysine1.png',
             '../assets/images/lysine2.png',
             '../assets/images/lysine3.png',
             '../assets/images/lysine4.png']
},
{
  "name": "arginine",
  "carboxyl_pka": 2.17,
  "amino_pka": 9.04,
  "side_pka": 12.48,
  "pi": 10.76,
  "states": ['../assets/images/arginine1.png',
             '../assets/images/arginine2.png',
             '../assets/images/arginine3.png',
             '../assets/images/arginine4.png']
},
{
  "name": "histidine",
  "carboxyl_pka": 1.82,
  "amino_pka": 9.17,
  "side_pka": 6.00,
  "pi": 7.59,
  "states": ['../assets/images/histidine1.png',
             '../assets/images/histidine2.png',
             '../assets/images/histidine3.png',
             '../assets/images/histidine4.png']
}
